riptide_cpp.cp312-win_amd64.pyd
riptide_cpp-1.19.0.dist-info/METADATA
riptide_cpp-1.19.0.dist-info/WHEEL
riptide_cpp-1.19.0.dist-info/entry_points.txt
riptide_cpp-1.19.0.dist-info/licenses/LICENSE
riptide_cpp-1.19.0.dist-info/RECORD
