Metadata-Version: 2.1
Name: riptide_cpp
Version: 1.19.0
Summary: Python Package with fast math util functions
Author-Email: RTOS Holdings <rtosholdings-bot@sig.com>
License: BSD 3-Clause License
Classifier: Development Status :: 4 - Beta
Classifier: Intended Audience :: Developers
Classifier: Programming Language :: Python :: 3
Classifier: Programming Language :: Python :: 3.10
Classifier: Programming Language :: Python :: 3.11
Classifier: Programming Language :: Python :: 3.12
Classifier: License :: OSI Approved :: BSD License
Project-URL: Repository, https://github.com/rtosholdings/riptide_cpp
Project-URL: Documentation, https://riptable.readthedocs.io/en/stable/
Requires-Python: >=3.10
License-File: LICENSE
